{
  "main": {
    "id": "63a9f5d1ebbf01eb",
    "type": "split",
    "children": [
      {
        "id": "b52d6836a42b842b",
        "type": "tabs",
        "children": [
          {
            "id": "41882cd081145c8b",
            "type": "leaf",
            "state": {
              "type": "empty",
              "state": {}
            }
          }
        ]
      }
    ],
    "direction": "vertical"
  },
  "left": {
    "id": "6e10b76e7379be9c",
    "type": "split",
    "children": [
      {
        "id": "8bd80d674a3d0a31",
        "type": "tabs",
        "children": [
          {
            "id": "529de101a363e3ee",
            "type": "leaf",
            "state": {
              "type": "file-explorer",
              "state": {
                "sortOrder": "alphabetical"
              }
            }
          },
          {
            "id": "bd1deacd9adb3421",
            "type": "leaf",
            "state": {
              "type": "search",
              "state": {
                "query": "",
                "matchingCase": false,
                "explainSearch": false,
                "collapseAll": false,
                "extraContext": false,
                "sortOrder": "alphabetical"
              }
            }
          },
          {
            "id": "c625097b5f128d69",
            "type": "leaf",
            "state": {
              "type": "bookmarks",
              "state": {}
            }
          }
        ]
      }
    ],
    "direction": "horizontal",
    "width": 300
  },
  "right": {
    "id": "d304599a7e8dda25",
    "type": "split",
    "children": [
      {
        "id": "3fce7a7ae3a92caa",
        "type": "tabs",
        "children": [
          {
            "id": "487db0d063a447e6",
            "type": "leaf",
            "state": {
              "type": "backlink",
              "state": {
                "collapseAll": false,
                "extraContext": false,
                "sortOrder": "alphabetical",
                "showSearch": false,
                "searchQuery": "",
                "backlinkCollapsed": false,
                "unlinkedCollapsed": true
              }
            }
          },
          {
            "id": "c771133fcd17c7d6",
            "type": "leaf",
            "state": {
              "type": "outgoing-link",
              "state": {
                "linksCollapsed": false,
                "unlinkedCollapsed": true
              }
            }
          },
          {
            "id": "e2d61a7ed9314e2a",
            "type": "leaf",
            "state": {
              "type": "tag",
              "state": {
                "sortOrder": "frequency",
                "useHierarchy": true
              }
            }
          },
          {
            "id": "ed33f186faa2a711",
            "type": "leaf",
            "state": {
              "type": "outline",
              "state": {}
            }
          }
        ]
      }
    ],
    "direction": "horizontal",
    "width": 300,
    "collapsed": true
  },
  "left-ribbon": {
    "hiddenItems": {
      "switcher:Open quick switcher": false,
      "graph:Open graph view": false,
      "canvas:Create new canvas": false,
      "daily-notes:Open today's daily note": false,
      "templates:Insert template": false,
      "command-palette:Open command palette": false
    }
  },
  "active": "41882cd081145c8b",
  "lastOpenFiles": []
}